{
  "schema_version": 1,
  "generated_from": "registry_manifest.json",
  "populate_scope": [
    "A0",
    "A1",
    "A2"
  ],
  "target_counts_by_level": {
    "A0": 59,
    "A1": 116,
    "A2": 90
  },
  "target_counts_by_registry": {
    "core_interaction_chunk": 35,
    "discourse_pattern": 30,
    "grammar_construction": 93,
    "interactional_function": 30,
    "orthography_feature": 16,
    "particle_function": 26,
    "phonology_feature": 22,
    "register_feature": 13
  },
  "situation_pack_connections": {
    "appointments_scheduling": 4,
    "banking_payment": 4,
    "cafe_ordering": 6,
    "clinic_pharmacy": 4,
    "conflict_repair": 4,
    "daily_routine": 4,
    "delivery_pickup": 4,
    "directions_location": 4,
    "education_work": 4,
    "emergency_problem_reporting": 4,
    "family_relationships": 4,
    "field_work": 4,
    "food_service_work": 4,
    "housing_home": 4,
    "invitations_plans": 4,
    "logistics_work": 4,
    "making_friends": 4,
    "medical_work": 4,
    "messaging_calls": 4,
    "mobile_internet": 4,
    "neighborhood_life": 4,
    "office_work": 4,
    "preferences_opinions": 5,
    "public_services": 4,
    "restaurant_ordering": 4,
    "self_introduction": 4,
    "service_work": 4,
    "shopping_checkout": 4,
    "small_talk": 4,
    "survival_basics": 5,
    "transport_navigation": 4,
    "workplace_core": 4
  },
  "active_pack_count": 26,
  "active_pack_refs": [
    "appointments_scheduling",
    "banking_payment",
    "cafe_ordering",
    "clinic_pharmacy",
    "conflict_repair",
    "daily_routine",
    "delivery_pickup",
    "directions_location",
    "emergency_problem_reporting",
    "family_relationships",
    "housing_home",
    "invitations_plans",
    "making_friends",
    "messaging_calls",
    "mobile_internet",
    "neighborhood_life",
    "office_work",
    "preferences_opinions",
    "public_services",
    "restaurant_ordering",
    "self_introduction",
    "shopping_checkout",
    "small_talk",
    "survival_basics",
    "transport_navigation",
    "workplace_core"
  ],
  "reserved_pack_count": 6,
  "reserved_pack_refs": [
    "education_work",
    "field_work",
    "food_service_work",
    "logistics_work",
    "medical_work",
    "service_work"
  ],
  "empty_pack_refs": [],
  "profile_count": 5,
  "active_overlay_refs": [
    "heritage_oral",
    "heritage_reconnection",
    "korea_resident_worker"
  ],
  "reserved_profile_refs": [
    "topik_exam"
  ],
  "phonology_count": 22,
  "orthography_count": 16,
  "source_less_target_refs": [],
  "draft_or_low_confidence_target_refs": [],
  "active_core_without_source_evidence": [],
  "warnings": [],
  "blockers": [],
  "coverage_status": "pass"
}
